casatools/__init__.py
casatools/agentflagger.py
casatools/atcafiller.py
casatools/atmosphere.py
casatools/calanalysis.py
casatools/calibrater.py
casatools/coercetype.py
casatools/componentlist.py
casatools/constants.py
casatools/coordsys.py
casatools/errors.py
casatools/functional.py
casatools/image.py
casatools/imagemetadata.py
casatools/imagepol.py
casatools/imager.py
casatools/iterbotsink.py
casatools/linearmosaic.py
casatools/logsink.py
casatools/measures.py
casatools/miriadfiller.py
casatools/ms.py
casatools/msmetadata.py
casatools/mstransformer.py
casatools/msuvbinner.py
casatools/platform.py
casatools/quanta.py
casatools/regionmanager.py
casatools/sakura.py
casatools/sdm.py
casatools/sidebandseparator.py
casatools/simulator.py
casatools/singledishms.py
casatools/spectralline.py
casatools/synthesisdeconvolver.py
casatools/synthesisimager.py
casatools/synthesisimstore.py
casatools/synthesismaskhandler.py
casatools/synthesisnormalizer.py
casatools/synthesisutils.py
casatools/table.py
casatools/tablerow.py
casatools/typecheck.py
casatools/utils.py
casatools/vlafiller.py
casatools/vpmanager.py
casatools/wvr.py
casatools/__casac__/_agentflagger.cpython-312-x86_64-linux-gnu.so
casatools/__casac__/_atcafiller.cpython-312-x86_64-linux-gnu.so
casatools/__casac__/_atmosphere.cpython-312-x86_64-linux-gnu.so
casatools/__casac__/_calanalysis.cpython-312-x86_64-linux-gnu.so
casatools/__casac__/_calibrater.cpython-312-x86_64-linux-gnu.so
casatools/__casac__/_componentlist.cpython-312-x86_64-linux-gnu.so
casatools/__casac__/_coordsys.cpython-312-x86_64-linux-gnu.so
casatools/__casac__/_functional.cpython-312-x86_64-linux-gnu.so
casatools/__casac__/_image.cpython-312-x86_64-linux-gnu.so
casatools/__casac__/_imagemetadata.cpython-312-x86_64-linux-gnu.so
casatools/__casac__/_imagepol.cpython-312-x86_64-linux-gnu.so
casatools/__casac__/_imager.cpython-312-x86_64-linux-gnu.so
casatools-6.7.2.42.dist-info/METADATA
casatools-6.7.2.42.dist-info/WHEEL
casatools-6.7.2.42.dist-info/top_level.txt
casatools-6.7.2.42.dist-info/RECORD
