Metadata-Version: 2.4
Name: casatools
Version: 6.7.2.42
Summary: Astronomy data reduction library
Home-page: https://open-bitbucket.nrao.edu/projects/CASA/repos/casa6/browse
Author: CASA development team
Author-email: casa-feedback@nrao.edu
License: GPLv2
Classifier: Programming Language :: C
Classifier: Programming Language :: C++
Classifier: Programming Language :: Python :: 3.6
Classifier: Programming Language :: Python :: 3.7
Classifier: Programming Language :: Python :: 3.8
Classifier: Programming Language :: Python :: 3.9
Classifier: Programming Language :: Python :: 3.10
Classifier: Programming Language :: Python :: Implementation :: CPython
Classifier: Development Status :: 5 - Production/Stable
Classifier: Environment :: Console
Classifier: Intended Audience :: Science/Research
Classifier: Intended Audience :: Developers
Classifier: License :: OSI Approved :: GNU Library or Lesser General Public License (LGPL)
Classifier: Operating System :: POSIX
Classifier: Topic :: Scientific/Engineering :: Astronomy
Classifier: Topic :: Software Development :: Libraries :: Application Frameworks
Requires-Python: >=3.6
Requires-Dist: numpy
Requires-Dist: casaconfig
